nshsnap/.nshconfig.generated.json
nshsnap/__init__.py
nshsnap/_config.py
nshsnap/_load.py
nshsnap/_meta.py
nshsnap/_pip_deps.py
nshsnap/_snapshot.py
nshsnap/_util.py
nshsnap/cli.py
nshsnap/configs/.gitattributes
nshsnap/configs/SnapshotConfig_typed_dict.py
nshsnap/configs/__init__.py
nshsnap/configs/_config/EditablePackageDependency_typed_dict.py
nshsnap/configs/_config/SnapshotConfig_typed_dict.py
nshsnap/configs/_config/__init__.py
nshsnap/configs/_meta/SnapshotConfig_typed_dict.py
nshsnap/configs/_meta/SnapshotMetadata_typed_dict.py
nshsnap/configs/_meta/__init__.py
nshsnap/configs/_pip_deps/BasePackageDependency_typed_dict.py
nshsnap/configs/_pip_deps/EditablePackageDependency_typed_dict.py
nshsnap/configs/_pip_deps/RegularPackageDependency_typed_dict.py
nshsnap/configs/_pip_deps/__init__.py
nshsnap/configs/_snapshot/SnapshotConfig_typed_dict.py
nshsnap/configs/_snapshot/SnapshotMetadata_typed_dict.py
nshsnap/configs/_snapshot/__init__.py
nshsnap/configs/cli/SnapshotConfig_typed_dict.py
nshsnap/configs/cli/__init__.py
nshsnap-0.14.1.dist-info/LICENSE
nshsnap-0.14.1.dist-info/METADATA
nshsnap-0.14.1.dist-info/WHEEL
nshsnap-0.14.1.dist-info/entry_points.txt
nshsnap-0.14.1.dist-info/RECORD
