Metadata-Version: 2.3
Name: nshsnap
Version: 0.14.1
Summary: 
Author: Nima Shoghi
Author-email: nimashoghi@gmail.com
Requires-Python: >=3.9,<4.0
Classifier: Programming Language :: Python :: 3
Classifier: Programming Language :: Python :: 3.9
Classifier: Programming Language :: Python :: 3.10
Classifier: Programming Language :: Python :: 3.11
Classifier: Programming Language :: Python :: 3.12
Classifier: Programming Language :: Python :: 3.13
Provides-Extra: extra
Requires-Dist: nshconfig
Requires-Dist: uuid7
Project-URL: Homepage, https://github.com/nimashoghi/nshsnap
